<?xml version="1.0" encoding="UTF-8"?>
<!DOCTYPE mapper PUBLIC "-//mybatis.org//DTD Mapper 3.0//EN" "http://mybatis.org/dtd/mybatis-3-mapper.dtd">
<mapper namespace="cn.edu.upc.manage.dao.UserMapper">
  <resultMap id="BaseResultMap" type="cn.edu.upc.manage.model.User">
    <!--
      WARNING - @mbg.generated
      This element is automatically generated by MyBatis Generator, do not modify.
      This element was generated on Sun May 10 16:37:05 CST 2020.
    -->
    <id column="id" jdbcType="INTEGER" property="id" />
    <result column="user_name" jdbcType="VARCHAR" property="userName" />
    <result column="password" jdbcType="VARCHAR" property="password" />
    <result column="role_id" jdbcType="INTEGER" property="roleId" />
    <result column="user_type" jdbcType="INTEGER" property="userType" />
    <result column="department_unit_id" jdbcType="INTEGER" property="departmentUnitId" />
    <result column="email" jdbcType="VARCHAR" property="email" />
    <result column="creat_time" jdbcType="TIMESTAMP" property="creatTime" />
    <result column="del_flag" jdbcType="INTEGER" property="delFlag" />
    <result column="operator" jdbcType="VARCHAR" property="operator" />
    <result column="operator_ip" jdbcType="VARCHAR" property="operatorIp" />
    <result column="operator_time" jdbcType="TIMESTAMP" property="operatorTime" />
  </resultMap>
  <sql id="Base_Column_List">
    <!--
      WARNING - @mbg.generated
      This element is automatically generated by MyBatis Generator, do not modify.
      This element was generated on Sun May 10 16:37:05 CST 2020.
    -->
    id, user_name, password, role_id, user_type, department_unit_id, email, creat_time, 
    del_flag, operator, operator_ip, operator_time
  </sql>

  <resultMap id="UserWithUnitName" type="cn.edu.upc.manage.model.UserWithUnitName" extends="BaseResultMap">
    <result column="user_type_name" jdbcType="VARCHAR" property="userTypeName"/>
    <result column="unit_name" jdbcType="VARCHAR" property="unitName"/>
  </resultMap>

  <select id="selectByPrimaryKey" parameterType="java.lang.Integer" resultMap="BaseResultMap">
    <!--
      WARNING - @mbg.generated
      This element is automatically generated by MyBatis Generator, do not modify.
      This element was generated on Sun May 10 16:37:05 CST 2020.
    -->
    select 
    <include refid="Base_Column_List" />
    from user
    where id = #{id,jdbcType=INTEGER}
  </select>
  <delete id="deleteByPrimaryKey" parameterType="java.lang.Integer">
    <!--
      WARNING - @mbg.generated
      This element is automatically generated by MyBatis Generator, do not modify.
      This element was generated on Sun May 10 16:37:05 CST 2020.
    -->
    delete from user
    where id = #{id,jdbcType=INTEGER}
  </delete>
  <insert id="insert" parameterType="cn.edu.upc.manage.model.User">
    <!--
      WARNING - @mbg.generated
      This element is automatically generated by MyBatis Generator, do not modify.
      This element was generated on Sun May 10 16:37:05 CST 2020.
    -->
    insert into user (id, user_name, password, 
      role_id, user_type, department_unit_id, 
      email, creat_time, del_flag, 
      operator, operator_ip, operator_time
      )
    values (#{id,jdbcType=INTEGER}, #{userName,jdbcType=VARCHAR}, #{password,jdbcType=VARCHAR}, 
      #{roleId,jdbcType=INTEGER}, #{userType,jdbcType=INTEGER}, #{departmentUnitId,jdbcType=INTEGER}, 
      #{email,jdbcType=VARCHAR}, #{creatTime,jdbcType=TIMESTAMP}, #{delFlag,jdbcType=INTEGER}, 
      #{operator,jdbcType=VARCHAR}, #{operatorIp,jdbcType=VARCHAR}, #{operatorTime,jdbcType=TIMESTAMP}
      )
  </insert>
  <insert id="insertSelective" parameterType="cn.edu.upc.manage.model.User">
    <!--
      WARNING - @mbg.generated
      This element is automatically generated by MyBatis Generator, do not modify.
      This element was generated on Sun May 10 16:37:05 CST 2020.
    -->
    insert into user
    <trim prefix="(" suffix=")" suffixOverrides=",">
      <if test="id != null">
        id,
      </if>
      <if test="userName != null">
        user_name,
      </if>
      <if test="password != null">
        password,
      </if>
      <if test="roleId != null">
        role_id,
      </if>
      <if test="userType != null">
        user_type,
      </if>
      <if test="departmentUnitId != null">
        department_unit_id,
      </if>
      <if test="email != null">
        email,
      </if>
      <if test="creatTime != null">
        creat_time,
      </if>
      <if test="delFlag != null">
        del_flag,
      </if>
      <if test="operator != null">
        operator,
      </if>
      <if test="operatorIp != null">
        operator_ip,
      </if>
      <if test="operatorTime != null">
        operator_time,
      </if>
    </trim>
    <trim prefix="values (" suffix=")" suffixOverrides=",">
      <if test="id != null">
        #{id,jdbcType=INTEGER},
      </if>
      <if test="userName != null">
        #{userName,jdbcType=VARCHAR},
      </if>
      <if test="password != null">
        #{password,jdbcType=VARCHAR},
      </if>
      <if test="roleId != null">
        #{roleId,jdbcType=INTEGER},
      </if>
      <if test="userType != null">
        #{userType,jdbcType=INTEGER},
      </if>
      <if test="departmentUnitId != null">
        #{departmentUnitId,jdbcType=INTEGER},
      </if>
      <if test="email != null">
        #{email,jdbcType=VARCHAR},
      </if>
      <if test="creatTime != null">
        #{creatTime,jdbcType=TIMESTAMP},
      </if>
      <if test="delFlag != null">
        #{delFlag,jdbcType=INTEGER},
      </if>
      <if test="operator != null">
        #{operator,jdbcType=VARCHAR},
      </if>
      <if test="operatorIp != null">
        #{operatorIp,jdbcType=VARCHAR},
      </if>
      <if test="operatorTime != null">
        #{operatorTime,jdbcType=TIMESTAMP},
      </if>
    </trim>
  </insert>
  <update id="updateByPrimaryKeySelective" parameterType="cn.edu.upc.manage.model.User">
    <!--
      WARNING - @mbg.generated
      This element is automatically generated by MyBatis Generator, do not modify.
      This element was generated on Sun May 10 16:37:05 CST 2020.
    -->
    update user
    <set>
      <if test="userName != null">
        user_name = #{userName,jdbcType=VARCHAR},
      </if>
      <if test="password != null">
        password = #{password,jdbcType=VARCHAR},
      </if>
      <if test="roleId != null">
        role_id = #{roleId,jdbcType=INTEGER},
      </if>
      <if test="userType != null">
        user_type = #{userType,jdbcType=INTEGER},
      </if>
      <if test="departmentUnitId != null">
        department_unit_id = #{departmentUnitId,jdbcType=INTEGER},
      </if>
      <if test="email != null">
        email = #{email,jdbcType=VARCHAR},
      </if>
      <if test="creatTime != null">
        creat_time = #{creatTime,jdbcType=TIMESTAMP},
      </if>
      <if test="delFlag != null">
        del_flag = #{delFlag,jdbcType=INTEGER},
      </if>
      <if test="operator != null">
        operator = #{operator,jdbcType=VARCHAR},
      </if>
      <if test="operatorIp != null">
        operator_ip = #{operatorIp,jdbcType=VARCHAR},
      </if>
      <if test="operatorTime != null">
        operator_time = #{operatorTime,jdbcType=TIMESTAMP},
      </if>
    </set>
    where id = #{id,jdbcType=INTEGER}
  </update>
  <update id="updateByPrimaryKey" parameterType="cn.edu.upc.manage.model.User">
    <!--
      WARNING - @mbg.generated
      This element is automatically generated by MyBatis Generator, do not modify.
      This element was generated on Sun May 10 16:37:05 CST 2020.
    -->
    update user
    set user_name = #{userName,jdbcType=VARCHAR},
      password = #{password,jdbcType=VARCHAR},
      role_id = #{roleId,jdbcType=INTEGER},
      user_type = #{userType,jdbcType=INTEGER},
      department_unit_id = #{departmentUnitId,jdbcType=INTEGER},
      email = #{email,jdbcType=VARCHAR},
      creat_time = #{creatTime,jdbcType=TIMESTAMP},
      del_flag = #{delFlag,jdbcType=INTEGER},
      operator = #{operator,jdbcType=VARCHAR},
      operator_ip = #{operatorIp,jdbcType=VARCHAR},
      operator_time = #{operatorTime,jdbcType=TIMESTAMP}
    where id = #{id,jdbcType=INTEGER}
  </update>

  <select id="selectByUsername" resultMap="BaseResultMap">
    select * from user where user_name='${username}' and del_flag = 0
  </select>

  <update id="changePasswordByEmail" >
    update user set password='${newPassword}' where email='${email}'
  </update>

  <select id="selectByEmail" resultMap="BaseResultMap">
    select * from user where email='${email}' and del_flag=0
  </select>

  <update id="changePassword" >
    update user set password='${newPassword}' where id='${id}'
  </update>

  <update id="deleteUser">
    update user set del_flag='${userId}' where id='${userId}'
  </update>

  <select id="getAllUser" resultMap="UserWithUnitName">
    select * ,
case user.user_type
				when 1 then '集团管理用户'
				when 2 then '建设单位用户'
				end as user_type_name
from user where del_flag=0
  </select>
</mapper>